gh_webhooks/__init__.py
gh_webhooks/base.py
gh_webhooks/exceptions.py
gh_webhooks/handler.py
gh_webhooks/resolve_event.py
gh_webhooks/types.py
gh_webhooks-0.6.0.dist-info/LICENSE.md
gh_webhooks-0.6.0.dist-info/WHEEL
gh_webhooks-0.6.0.dist-info/METADATA
gh_webhooks-0.6.0.dist-info/RECORD
