Metadata-Version: 2.1
Name: gh-webhooks
Version: 0.6.0
Summary: Typed event handling for GitHub Webhooks
Home-page: https://github.com/k2bd/gh-webhooks
License: MIT
Author: Kevin Duff
Author-email: kevinkelduff@gmail.com
Requires-Python: >=3.7,<4.0
Classifier: Development Status :: 1 - Planning
Classifier: Intended Audience :: Developers
Classifier: License :: OSI Approved :: MIT License
Classifier: Operating System :: OS Independent
Classifier: Programming Language :: Python :: 3
Classifier: Programming Language :: Python :: 3.7
Classifier: Programming Language :: Python :: 3.8
Classifier: Programming Language :: Python :: 3.9
Classifier: Programming Language :: Python :: 3.10
Classifier: Programming Language :: Python :: 3
Classifier: Programming Language :: Python :: 3 :: Only
Classifier: Programming Language :: Python :: 3.10
Classifier: Programming Language :: Python :: 3.7
Classifier: Programming Language :: Python :: 3.8
Classifier: Programming Language :: Python :: 3.9
Provides-Extra: docs
Requires-Dist: pydantic[email] (==1.9.0)
Requires-Dist: stringcase (>=1.2.0,<2.0.0)
Requires-Dist: typing-extensions (>=4.2.0,<5.0.0)
Project-URL: Repository, https://github.com/k2bd/gh-webhooks
